<?xml version="1.0" encoding="UTF-8"?>
<code-table xml:id="genre-dct-genre-code">
    <code-table-name>genre-dct-genre-code</code-table-name>
    <status>finished</status>
    <form>closed</form>
    <basis>http://dublincore.org/documents/resource-typelist/</basis>
    <description>Dublin Core List of Resource Types</description>
    <notes>NB: label serves as value!</notes>
    <tab-id>location</tab-id>
    <tab-id>physical-description</tab-id>
    <tab-id>subject</tab-id>
    <tab-id>genre</tab-id>
    <tab-id>related</tab-id>
    <tab-id>related-abbreviated</tab-id>
    <items>
        <item>
            <label>(none selected)</label>
            <value/>
        </item>
        <item>
            <label>collection</label>
            <value>collection</value>
        </item>
        <item>
            <label>dataset</label>
            <value>dataset</value>
        </item>
        <item>
            <label>event</label>
            <value>event</value>
        </item>
        <item>
            <label>image</label>
            <value>image</value>
        </item>
        <item>
            <label>interactive resource</label>
            <value>interactive resource</value>
        </item>
        <item>
            <label>model</label>
            <value>model</value>
        </item>
        <item>
            <label>party</label>
            <value>party</value>
        </item>
        <item>
            <label>physical object</label>
            <value>physical object</value>
        </item>
        <item>
            <label>place</label>
            <value>place</value>
        </item>
        <item>
            <label>service</label>
            <value>service</value>
        </item>
        <item>
            <label>software</label>
            <value>software</value>
        </item>
        <item>
            <label>sound</label>
            <value>sound</value>
        </item>
        <item>
            <label>text</label>
            <value>text</value>
        </item>
    </items>
</code-table>